[
  {
    "date": "2025-04-10T22:00:00Z",
    "close": 5
  },
  {
    "date": "2025-04-13T22:00:00Z",
    "close": 5
  },
  {
    "date": "2025-04-14T22:00:00Z",
    "close": 5
  },
  {
    "date": "2025-04-15T22:00:00Z",
    "close": 5
  },
  {
    "date": "2025-04-16T22:00:00Z",
    "close": 5
  },
  {
    "date": "2025-04-21T22:00:00Z",
    "close": 5
  },
  {
    "date": "2025-04-22T22:00:00Z",
    "close": 5
  },
  {
    "date": "2025-04-23T22:00:00Z",
    "close": 5
  },
  {
    "date": "2025-04-27T22:00:00Z",
    "close": 5
  },
  {
    "date": "2025-04-28T22:00:00Z",
    "close": 5
  },
  {
    "date": "2025-04-29T22:00:00Z",
    "close": 5.006
  },
  {
    "date": "2025-05-01T22:00:00Z",
    "close": 5.006
  },
  {
    "date": "2025-05-04T22:00:00Z",
    "close": 5.006
  },
  {
    "date": "2025-05-05T22:00:00Z",
    "close": 5.007
  },
  {
    "date": "2025-05-06T22:00:00Z",
    "close": 5.012
  },
  {
    "date": "2025-05-07T22:00:00Z",
    "close": 5.008
  }
]